{
    "optimizer": "adam",
    "datadir": "dataset",
    "device": "cuda",
    "device_id": "0",
    "dataset": "IMAGENET1k",
    "num_classes": 1000,
    "model": "CNN",
    "batch_size": 64,
    "local_learning_rate": 0.01,
    "learning_rate_decay": false,
    "learning_rate_decay_gamma": 0.99,
    "global_rounds": 100,
    "local_epochs": 3,
    "algorithm": "FedSTGM",
    "join_ratio": 1.0,
    "random_join_ratio": false,
    "num_clients": 10,
    "prev": 0,
    "times": 1,
    "eval_gap": 1,
    "out_folder": "out",
    "note": "stgm_rounds=100, stgm_learning_rate=5, stgm_momentum=0.5, stgm_step_size=50, stgm_gamma=1.0, stgm_c=0.1, stgm_meta_lr=0.5, grad_balance=True, local_epochs=3, local_learning_rate=0.01",
    "num_tasks": 500,
    "client_drop_rate": 0.0,
    "time_threthold": 10000,
    "stgm_rounds": 100,
    "stgm_learning_rate": 5,
    "stgm_momentum": 0.5,
    "stgm_step_size": 50,
    "stgm_gamma": 1.0,
    "stgm_c": 0.1,
    "stgm_meta_lr": 0.5,
    "grad_balance": true,
    "coreset": false,
    "tgm": false,
    "sgm": true
}